zerottmm/__init__.py
zerottmm/ai_analysis.py
zerottmm/cli.py
zerottmm/gitingest.py
zerottmm/gitutils.py
zerottmm/index.py
zerottmm/metrics.py
zerottmm/search.py
zerottmm/store.py
zerottmm/trace.py
zerottmm-0.1.0.dist-info/METADATA
zerottmm-0.1.0.dist-info/WHEEL
zerottmm-0.1.0.dist-info/entry_points.txt
zerottmm-0.1.0.dist-info/top_level.txt
zerottmm-0.1.0.dist-info/RECORD
