Metadata-Version: 2.4
Name: zerottmm
Version: 0.1.0
Summary: Time‑to‑Mental‑Model: a local‑first code reading assistant (Phase A)
Author-email: Gaurav Sood <contact@gsood.com>
License-Expression: MIT
Keywords: code-analysis,static-analysis,code-reading,python,ast
Classifier: Development Status :: 4 - Beta
Classifier: Intended Audience :: Developers
Classifier: Programming Language :: Python :: 3
Classifier: Programming Language :: Python :: 3.10
Classifier: Programming Language :: Python :: 3.11
Classifier: Programming Language :: Python :: 3.12
Classifier: Programming Language :: Python :: 3.13
Classifier: Topic :: Software Development :: Code Generators
Classifier: Topic :: Software Development :: Libraries :: Python Modules
Classifier: Topic :: Utilities
Requires-Python: >=3.10
Provides-Extra: ui
Requires-Dist: streamlit>=1.23; extra == "ui"
Requires-Dist: openai>=1.0.0; extra == "ui"
Provides-Extra: test
Requires-Dist: pytest; extra == "test"
Provides-Extra: ai
Requires-Dist: openai>=1.0.0; extra == "ai"
Provides-Extra: all
Requires-Dist: streamlit>=1.23; extra == "all"
Requires-Dist: pytest; extra == "all"
Requires-Dist: openai>=1.0.0; extra == "all"
